yeast/__init__.py
yeast/collect_features.py
sgd_chromosomal_features-1.0.2.dist-info/LICENSE
sgd_chromosomal_features-1.0.2.dist-info/METADATA
sgd_chromosomal_features-1.0.2.dist-info/WHEEL
sgd_chromosomal_features-1.0.2.dist-info/entry_points.txt
sgd_chromosomal_features-1.0.2.dist-info/top_level.txt
sgd_chromosomal_features-1.0.2.dist-info/RECORD
